{
  "timestamp": "2026-07-23T15:15:26.109480+00:00",
  "picks": [
    {
      "symbol": "ALLE",
      "price": 155.29,
      "change_pct": 10.96,
      "buy_pct": 96,
      "sell_pct": 4,
      "volatility_pct": 5.12,
      "entry": 155.29,
      "stop_loss": 151.32,
      "target_1": 161.25,
      "target_2": 167.21,
      "risk_reward": 1.5,
      "final_score": 87,
      "pe_ratio": 18.9786,
      "news_label": "positiv",
      "rsi": null,
      "trend_label": "unbekannt",
      "volume_label": "unbekannt",
      "target_basis": "tagesspanne",
      "chart": [],
      "timestamp": "2026-07-23T15:15:26.109480+00:00",
      "fundamental_score": 93,
      "news_score": 100,
      "momentum_quality": 50
    },
    {
      "symbol": "LMT",
      "price": 566.16,
      "change_pct": 10.07,
      "buy_pct": 88,
      "sell_pct": 12,
      "volatility_pct": 5.39,
      "entry": 566.16,
      "stop_loss": 550.91,
      "target_1": 589.03,
      "target_2": 611.91,
      "risk_reward": 1.5,
      "final_score": 84,
      "pe_ratio": 24.8415,
      "news_label": "positiv",
      "rsi": null,
      "trend_label": "unbekannt",
      "volume_label": "unbekannt",
      "target_basis": "tagesspanne",
      "chart": [],
      "timestamp": "2026-07-23T15:15:26.109480+00:00",
      "fundamental_score": 92,
      "news_score": 100,
      "momentum_quality": 50
    },
    {
      "symbol": "URI",
      "price": 1156.97,
      "change_pct": 11.78,
      "buy_pct": 96,
      "sell_pct": 4,
      "volatility_pct": 7.31,
      "entry": 1156.97,
      "stop_loss": 1114.7,
      "target_1": 1220.37,
      "target_2": 1283.76,
      "risk_reward": 1.5,
      "final_score": 79,
      "pe_ratio": 25.7717,
      "news_label": "positiv",
      "rsi": null,
      "trend_label": "unbekannt",
      "volume_label": "unbekannt",
      "target_basis": "tagesspanne",
      "chart": [],
      "timestamp": "2026-07-23T15:15:26.109480+00:00",
      "fundamental_score": 62,
      "news_score": 100,
      "momentum_quality": 50
    }
  ]
}