{
  "timestamp": "2026-07-23T19:45:21.653839+00:00",
  "picks": [
    {
      "symbol": "ALLE",
      "price": 155.49,
      "change_pct": 11.1,
      "buy_pct": 89,
      "sell_pct": 11,
      "volatility_pct": 6.85,
      "entry": 155.49,
      "stop_loss": 150.16,
      "target_1": 163.48,
      "target_2": 171.47,
      "risk_reward": 1.5,
      "final_score": 84,
      "pe_ratio": 18.9786,
      "news_label": "positiv",
      "rsi": null,
      "trend_label": "unbekannt",
      "volume_label": "unbekannt",
      "target_basis": "tagesspanne",
      "chart": [],
      "timestamp": "2026-07-23T19:45:21.653839+00:00",
      "fundamental_score": 93,
      "news_score": 100,
      "momentum_quality": 50
    },
    {
      "symbol": "LMT",
      "price": 566.87,
      "change_pct": 10.21,
      "buy_pct": 89,
      "sell_pct": 11,
      "volatility_pct": 5.47,
      "entry": 566.87,
      "stop_loss": 551.37,
      "target_1": 590.12,
      "target_2": 613.37,
      "risk_reward": 1.5,
      "final_score": 83,
      "pe_ratio": 27.5782,
      "news_label": "positiv",
      "rsi": null,
      "trend_label": "unbekannt",
      "volume_label": "unbekannt",
      "target_basis": "tagesspanne",
      "chart": [],
      "timestamp": "2026-07-23T19:45:21.653839+00:00",
      "fundamental_score": 89,
      "news_score": 100,
      "momentum_quality": 50
    },
    {
      "symbol": "MCK",
      "price": 822.53,
      "change_pct": 1.04,
      "buy_pct": 73,
      "sell_pct": 27,
      "volatility_pct": 1.54,
      "entry": 822.53,
      "stop_loss": 816.2,
      "target_1": 832.02,
      "target_2": 841.5,
      "risk_reward": 1.5,
      "final_score": 79,
      "pe_ratio": 20.1507,
      "news_label": "positiv",
      "rsi": null,
      "trend_label": "unbekannt",
      "volume_label": "unbekannt",
      "target_basis": "tagesspanne",
      "chart": [],
      "timestamp": "2026-07-23T19:45:21.653839+00:00",
      "fundamental_score": 93,
      "news_score": 100,
      "momentum_quality": 50
    }
  ]
}